sinchanpgs/__init__.py
sinchanpgs/pg1.py
sinchanpgs/pg10.py
sinchanpgs/pg11.py
sinchanpgs/pg12.py
sinchanpgs/pg2.py
sinchanpgs/pg3.py
sinchanpgs/pg4.py
sinchanpgs/pg5.py
sinchanpgs/pg6.py
sinchanpgs/pg7.py
sinchanpgs/pg8.py
sinchanpgs/pg9.py
SinchanDora-0.0.13.dist-info/LICENSE
SinchanDora-0.0.13.dist-info/METADATA
SinchanDora-0.0.13.dist-info/WHEEL
SinchanDora-0.0.13.dist-info/top_level.txt
SinchanDora-0.0.13.dist-info/RECORD
